Metadata-Version: 1.1
Name: pyvisage
Version: 0.15
Summary: Add virtual makeup to an image of a face.
Home-page: https://github.com/hriddhidey/visage.git
Author: Hriddhi Dey
Author-email: hriddhidey@gmail.com
License: UNKNOWN
Download-URL: https://github.com/hriddhidey/visage/archive/0.15.tar.gz
Keywords: image,processing,virtual,makeup,face,detection,opencv
Platform: UNKNOWN
